sirf_config/__init__.py
sirf_config/cli.py
sirf_config/config_loader.py
sirf_config/utils.py
sirf_config/default_configs/__init__.py
sirf_config/default_configs/protocols.yaml
sirf_config/default_configs/radionuclides.yaml
sirf_config/default_configs/scanners.yaml
sirf_config-0.1.0.dist-info/licenses/LICENSE
sirf_config-0.1.0.dist-info/METADATA
sirf_config-0.1.0.dist-info/WHEEL
sirf_config-0.1.0.dist-info/entry_points.txt
sirf_config-0.1.0.dist-info/top_level.txt
sirf_config-0.1.0.dist-info/RECORD
