Metadata-Version: 2.4
Name: sirf-config
Version: 0.1.0
Summary: Configuration management for SIRF SPECT/PET reconstruction workflows
Home-page: https://github.com/yourusername/sirf-config
Author: Your Name
Author-email: Sam Porter <sam.porter.18@ucl.ac.uk>
License: Apache License
Project-URL: Homepage, https://github.com/samdporter/sirf-config
Project-URL: Documentation, https://sirf-config.readthedocs.io
Project-URL: Repository, https://github.com/samdporter/sirf-config
Project-URL: Bug Tracker, https://github.com/samdporter/sirf-config/issues
Keywords: SIRF,SPECT,PET,medical imaging,reconstruction,configuration
Classifier: Development Status :: 4 - Beta
Classifier: Intended Audience :: Science/Research
Classifier: License :: OSI Approved :: Apache Software License
Classifier: Operating System :: OS Independent
Classifier: Programming Language :: Python :: 3
Classifier: Programming Language :: Python :: 3.8
Classifier: Programming Language :: Python :: 3.9
Classifier: Programming Language :: Python :: 3.10
Classifier: Programming Language :: Python :: 3.11
Classifier: Topic :: Scientific/Engineering :: Medical Science Apps.
Classifier: Topic :: Scientific/Engineering :: Physics
Requires-Python: >=3.8
License-File: LICENSE
Requires-Dist: pyyaml>=6.0
Requires-Dist: typing-extensions>=4.0.0; python_version < "3.10"
Provides-Extra: dev
Requires-Dist: pytest>=7.0; extra == "dev"
Requires-Dist: pytest-cov>=4.0; extra == "dev"
Requires-Dist: black>=22.0; extra == "dev"
Requires-Dist: flake8>=5.0; extra == "dev"
Requires-Dist: isort>=5.0; extra == "dev"
Requires-Dist: mypy>=1.0; extra == "dev"
Provides-Extra: docs
Requires-Dist: sphinx>=5.0; extra == "docs"
Requires-Dist: sphinx-rtd-theme>=1.0; extra == "docs"
Requires-Dist: myst-parser>=0.18; extra == "docs"
Provides-Extra: examples
Requires-Dist: matplotlib>=3.5; extra == "examples"
Requires-Dist: numpy>=1.20; extra == "examples"
Dynamic: author
Dynamic: home-page
Dynamic: license-file
Dynamic: requires-python
